odoo/addons/stock_move_backdating/README.rst
odoo/addons/stock_move_backdating/__init__.py
odoo/addons/stock_move_backdating/__manifest__.py
odoo/addons/stock_move_backdating/models/__init__.py
odoo/addons/stock_move_backdating/models/stock_move.py
odoo/addons/stock_move_backdating/models/stock_move_line.py
odoo/addons/stock_move_backdating/models/stock_picking.py
odoo/addons/stock_move_backdating/static/description/icon.png
odoo/addons/stock_move_backdating/views/stock_move_views.xml
odoo/addons/stock_move_backdating/views/stock_picking_views.xml
odoo14_addon_stock_move_backdating-14.0.1.2.0.dist-info/METADATA
odoo14_addon_stock_move_backdating-14.0.1.2.0.dist-info/WHEEL
odoo14_addon_stock_move_backdating-14.0.1.2.0.dist-info/top_level.txt
odoo14_addon_stock_move_backdating-14.0.1.2.0.dist-info/RECORD
